{"cameraMode":{"drawMode":0,"name":"Shaded","section":"Shading Mode"},"sceneLighting":true,"audioPlay":false,"sceneViewState":{"showFog":true,"showMaterialUpdate":false,"showSkybox":true,"showFlares":true,"showImageEffects":true,"showParticleSystems":true},"in2DMode":false,"pivot":{"x":19.800405502319337,"y":-9.723738670349121,"z":5.646228313446045},"rotation":{"x":0.1936851292848587,"y":0.5023759007453919,"z":-0.1149439811706543,"w":0.8351567983627319},"size":30.481035232543947,"orthographic":false}